[{"slug":"oc-tao-vang-lon","name":"Ốc táo vàng lớn","price":"60k/10con","cat":"oc","imgs":["images/oc-tao-vang-lon_0.jpg","images/oc-tao-vang-lon_1.jpg","images/oc-tao-vang-lon_2.jpg","images/oc-tao-vang-lon_3.jpg","images/oc-tao-vang-lon_4.jpg"]},{"slug":"oc-tao-tim-hong","name":"Ốc táo tím/hồng","price":"15k/1con","cat":"oc","imgs":["images/oc-tao-tim-hong_0.jpg","images/oc-tao-tim-hong_1.jpg","images/oc-tao-tim-hong_2.jpg","images/oc-tao-tim-hong_3.jpg","images/oc-tao-tim-hong_4.jpg"]},{"slug":"oc-nerita-van","name":"Ốc Nerita vằn","price":"65k/100con (lẻ 1,5k/1con)","cat":"oc","imgs":["images/oc-nerita-van_0.jpg","images/oc-nerita-van_1.jpg","images/oc-nerita-van_2.jpg","images/oc-nerita-van_3.jpg","images/oc-nerita-van_4.jpg"]},{"slug":"oc-nerita-thit-vang-mini","name":"Ốc Nerita thịt vàng mini","price":"35k/100con · 50k/250con (lẻ 0,5k/1con)","cat":"oc","imgs":["images/oc-nerita-thit-vang-mini_0.jpg","images/oc-nerita-thit-vang-mini_1.jpg","images/oc-nerita-thit-vang-mini_2.jpg","images/oc-nerita-thit-vang-mini_3.jpg","images/oc-nerita-thit-vang-mini_4.jpg"]},{"slug":"oc-helena-lon","name":"Ốc Helena lớn","price":"50k/10con","cat":"oc","imgs":["images/oc-helena-lon_0.jpg","images/oc-helena-lon_1.jpg","images/oc-helena-lon_2.jpg","images/oc-helena-lon_3.jpg","images/oc-helena-lon_4.jpg"]},{"slug":"tram-moi","name":"Trâm mồi","price":"50k/300con · 35k/150con","cat":"thuy-sinh","imgs":["images/tram-moi_0.jpg","images/tram-moi_1.jpg","images/tram-moi_2.jpg","images/tram-moi_3.jpg","images/tram-moi_4.jpg"]},{"slug":"canh-buom-du-mau","name":"Cánh buồm đủ màu","price":"4k/1con · 200k/100con","cat":"thuy-sinh","imgs":["images/canh-buom-du-mau_0.jpg","images/canh-buom-du-mau_1.jpg","images/canh-buom-du-mau_2.jpg","images/canh-buom-du-mau_3.jpg","images/canh-buom-du-mau_4.jpg"]},{"slug":"soc-ngua-canh-tien","name":"Sọc ngựa cánh tiên","price":"15k/1con","cat":"thuy-sinh","imgs":["images/soc-ngua-canh-tien_0.jpg","images/soc-ngua-canh-tien_1.jpg","images/soc-ngua-canh-tien_2.jpg","images/soc-ngua-canh-tien_3.jpg","images/soc-ngua-canh-tien_4.jpg"]},{"slug":"molly-platinum-short","name":"Molly Platinum Short","price":"35k","cat":"thuy-sinh","imgs":["images/molly-platinum-short_0.jpg","images/molly-platinum-short_1.jpg","images/molly-platinum-short_2.jpg","images/molly-platinum-short_3.jpg","images/molly-platinum-short_4.jpg"]},{"slug":"molly-ngua","name":"Molly Ngựa","price":"40k","cat":"thuy-sinh","imgs":["images/molly-ngua_0.jpg","images/molly-ngua_1.jpg","images/molly-ngua_2.jpg","images/molly-ngua_3.jpg","images/molly-ngua_4.jpg"]},{"slug":"mun-lua-short","name":"Mún Lửa Short","price":"20k","cat":"thuy-sinh","imgs":["images/mun-lua-short_0.jpg","images/mun-lua-short_1.jpg","images/mun-lua-short_2.jpg","images/mun-lua-short_3.jpg","images/mun-lua-short_4.jpg"]},{"slug":"mun-do-thuong","name":"Mún Đỏ thường","price":"45k/10con","cat":"thuy-sinh","imgs":["images/mun-do-thuong_0.jpg","images/mun-do-thuong_1.jpg","images/mun-do-thuong_2.jpg","images/mun-do-thuong_3.jpg","images/mun-do-thuong_4.jpg"]},{"slug":"diec-anh-dao-vdai-sieu-do","name":"Diếc Anh Đào v.dài siêu đỏ","price":"150k/10con","cat":"thuy-sinh","imgs":["images/diec-anh-dao-vdai-sieu-do_0.jpg","images/diec-anh-dao-vdai-sieu-do_1.jpg","images/diec-anh-dao-vdai-sieu-do_2.jpg","images/diec-anh-dao-vdai-sieu-do_3.jpg","images/diec-anh-dao-vdai-sieu-do_4.jpg"]},{"slug":"cat-keo","name":"Cắt kéo","price":"130k/10con","cat":"thuy-sinh","imgs":["images/cat-keo_0.jpg","images/cat-keo_1.jpg","images/cat-keo_2.jpg","images/cat-keo_3.jpg","images/cat-keo_4.jpg"]},{"slug":"soc-dau-do","name":"Sóc Đầu Đỏ","price":"70k/10con · 250k/50con","cat":"thuy-sinh","imgs":["images/soc-dau-do_0.jpg","images/soc-dau-do_1.jpg","images/soc-dau-do_2.jpg","images/soc-dau-do_3.jpg","images/soc-dau-do_4.jpg"]},{"slug":"neon-vua","name":"Neon Vua","price":"70k/10con · 250k/50con","cat":"thuy-sinh","imgs":["images/neon-vua_0.jpg","images/neon-vua_1.jpg","images/neon-vua_2.jpg","images/neon-vua_3.jpg","images/neon-vua_4.jpg"]},{"slug":"neon-den","name":"Neon Đen","price":"60k/10con","cat":"thuy-sinh","imgs":["images/neon-den_0.jpg","images/neon-den_1.jpg","images/neon-den_2.jpg","images/neon-den_3.jpg","images/neon-den_4.jpg"]},{"slug":"neon-kim-cuong","name":"Neon Kim Cương","price":"15k/1con","cat":"thuy-sinh","imgs":["images/neon-kim-cuong_0.jpg","images/neon-kim-cuong_1.jpg","images/neon-kim-cuong_2.jpg","images/neon-kim-cuong_3.jpg","images/neon-kim-cuong_4.jpg"]},{"slug":"hong-mi-4-5cm","name":"Hồng Mi size 4-5cm","price":"50k/1con","cat":"thuy-sinh","imgs":["images/hong-mi-4-5cm_0.jpg","images/hong-mi-4-5cm_1.jpg","images/hong-mi-4-5cm_2.jpg","images/hong-mi-4-5cm_3.jpg","images/hong-mi-4-5cm_4.jpg"]},{"slug":"hong-mi-8-10cm","name":"Hồng Mi size 8-10cm","price":"120k/1con","cat":"thuy-sinh","imgs":["images/hong-mi-8-10cm_0.jpg","images/hong-mi-8-10cm_1.jpg","images/hong-mi-8-10cm_2.jpg","images/hong-mi-8-10cm_3.jpg","images/hong-mi-8-10cm_4.jpg"]},{"slug":"hong-mi-tambra","name":"Hồng Mi Tambra","price":"75k","cat":"thuy-sinh","imgs":["images/hong-mi-tambra_0.jpg","images/hong-mi-tambra_1.jpg","images/hong-mi-tambra_2.jpg","images/hong-mi-tambra_3.jpg","images/hong-mi-tambra_4.jpg"]},{"slug":"tao-do-dai","name":"Táo Đỏ dài","price":"150k","cat":"thuy-sinh","imgs":["images/tao-do-dai_0.jpg","images/tao-do-dai_1.jpg","images/tao-do-dai_2.jpg","images/tao-do-dai_3.jpg","images/tao-do-dai_4.jpg"]},{"slug":"tao-do-short","name":"Táo Đỏ Short","price":"170k","cat":"thuy-sinh","imgs":["images/tao-do-short_0.jpg","images/tao-do-short_1.jpg","images/tao-do-short_2.jpg","images/tao-do-short_3.jpg","images/tao-do-short_4.jpg"]},{"slug":"trifas-dai","name":"Trifas dài","price":"150k","cat":"thuy-sinh","imgs":["images/trifas-dai_0.jpg","images/trifas-dai_1.jpg","images/trifas-dai_2.jpg","images/trifas-dai_3.jpg","images/trifas-dai_4.jpg"]},{"slug":"trifas-short","name":"Trifas short","price":"170k","cat":"thuy-sinh","imgs":["images/trifas-short_0.jpg","images/trifas-short_1.jpg","images/trifas-short_2.jpg","images/trifas-short_3.jpg","images/trifas-short_4.jpg"]},{"slug":"diec-vay-rong","name":"Diếc vảy rồng","price":"50k","cat":"thuy-sinh","imgs":["images/diec-vay-rong_0.jpg","images/diec-vay-rong_1.jpg","images/diec-vay-rong_2.jpg","images/diec-vay-rong_3.jpg","images/diec-vay-rong_4.jpg"]},{"slug":"thach-my-nhan-3-4","name":"Thạch Mỹ nhân 3-4","price":"100k","cat":"thuy-sinh","imgs":["images/thach-my-nhan-3-4_0.jpg","images/thach-my-nhan-3-4_1.jpg","images/thach-my-nhan-3-4_2.jpg","images/thach-my-nhan-3-4_3.jpg","images/thach-my-nhan-3-4_4.jpg"]},{"slug":"thach-my-nhan-do-5-6","name":"Thạch Mỹ Nhân Đỏ 5-6","price":"180k","cat":"thuy-sinh","imgs":["images/thach-my-nhan-do-5-6_0.jpg","images/thach-my-nhan-do-5-6_1.jpg","images/thach-my-nhan-do-5-6_2.jpg","images/thach-my-nhan-do-5-6_3.jpg","images/thach-my-nhan-do-5-6_4.jpg"]},{"slug":"congo-tetra","name":"Congo Tetra","price":"120k","cat":"thuy-sinh","imgs":["images/congo-tetra_0.jpg","images/congo-tetra_1.jpg","images/congo-tetra_2.jpg","images/congo-tetra_3.jpg","images/congo-tetra_4.jpg"]},{"slug":"phuong-hoang-lam","name":"Phượng Hoàng Lam","price":"40k","cat":"thuy-sinh","imgs":["images/phuong-hoang-lam_0.jpg","images/phuong-hoang-lam_1.jpg","images/phuong-hoang-lam_2.jpg","images/phuong-hoang-lam_3.jpg","images/phuong-hoang-lam_4.jpg"]},{"slug":"phuong-hoang-ngu-sac","name":"Phượng Hoàng Ngũ sắc","price":"40k","cat":"thuy-sinh","imgs":["images/phuong-hoang-ngu-sac_0.jpg","images/phuong-hoang-ngu-sac_1.jpg","images/phuong-hoang-ngu-sac_2.jpg","images/phuong-hoang-ngu-sac_3.jpg","images/phuong-hoang-ngu-sac_4.jpg"]},{"slug":"phuong-hoang-vang","name":"Phượng hoàng Vàng","price":"40k","cat":"thuy-sinh","imgs":["images/phuong-hoang-vang_0.jpg","images/phuong-hoang-vang_1.jpg","images/phuong-hoang-vang_2.jpg","images/phuong-hoang-vang_3.jpg","images/phuong-hoang-vang_4.jpg"]},{"slug":"xecan-short-vang","name":"Xecan short vàng","price":"50k","cat":"thuy-sinh","imgs":["images/xecan-short-vang_0.jpg","images/xecan-short-vang_1.jpg","images/xecan-short-vang_2.jpg","images/xecan-short-vang_3.jpg","images/xecan-short-vang_4.jpg"]},{"slug":"xecan-short-xanh","name":"Xecan short xanh","price":"60k","cat":"thuy-sinh","imgs":["images/xecan-short-xanh_0.jpg","images/xecan-short-xanh_1.jpg","images/xecan-short-xanh_2.jpg","images/xecan-short-xanh_3.jpg","images/xecan-short-xanh_4.jpg"]},{"slug":"xecan-short-tiger","name":"Xecan short tiger","price":"35k","cat":"thuy-sinh","imgs":["images/xecan-short-tiger_0.jpg","images/xecan-short-tiger_1.jpg","images/xecan-short-tiger_2.jpg","images/xecan-short-tiger_3.jpg","images/xecan-short-tiger_4.jpg"]},{"slug":"chuot-venezuela","name":"Chuột Venezuela","price":"25k","cat":"tang-day","imgs":["images/chuot-venezuela_0.jpg","images/chuot-venezuela_1.jpg","images/chuot-venezuela_2.jpg","images/chuot-venezuela_3.jpg","images/chuot-venezuela_4.jpg"]},{"slug":"chuot-cafe-canh-tien","name":"Chuột Cafe Cánh Tiên","price":"50k","cat":"tang-day","imgs":["images/chuot-cafe-canh-tien_0.jpg","images/chuot-cafe-canh-tien_1.jpg","images/chuot-cafe-canh-tien_2.jpg","images/chuot-cafe-canh-tien_3.jpg","images/chuot-cafe-canh-tien_4.jpg"]},{"slug":"chuot-cafe-thuong","name":"Chuột Cafe thường","price":"12k","cat":"tang-day","imgs":["images/chuot-cafe-thuong_0.jpg","images/chuot-cafe-thuong_1.jpg","images/chuot-cafe-thuong_2.jpg","images/chuot-cafe-thuong_3.jpg","images/chuot-cafe-thuong_4.jpg"]},{"slug":"chuot-my","name":"Chuột Mỹ","price":"80k","cat":"tang-day","imgs":["images/chuot-my_0.jpg","images/chuot-my_1.jpg","images/chuot-my_2.jpg","images/chuot-my_3.jpg","images/chuot-my_4.jpg"]},{"slug":"chuot-julli","name":"Chuột Julli","price":"25k","cat":"tang-day","imgs":["images/chuot-julli_0.jpg","images/chuot-julli_1.jpg","images/chuot-julli_2.jpg","images/chuot-julli_3.jpg","images/chuot-julli_4.jpg"]},{"slug":"chuot-sao","name":"Chuột Sao","price":"25k","cat":"tang-day","imgs":["images/chuot-sao_0.jpg","images/chuot-sao_1.jpg","images/chuot-sao_2.jpg","images/chuot-sao_3.jpg","images/chuot-sao_4.jpg"]},{"slug":"chuot-green-lon","name":"Chuột Green lớn","price":"55k","cat":"tang-day","imgs":["images/chuot-green-lon_0.jpg","images/chuot-green-lon_1.jpg","images/chuot-green-lon_2.jpg","images/chuot-green-lon_3.jpg","images/chuot-green-lon_4.jpg"]},{"slug":"chuot-albino-thuong","name":"Chuột Albino thường","price":"nhỏ 17k · lớn 35k","cat":"tang-day","imgs":["images/chuot-albino-thuong_0.jpg","images/chuot-albino-thuong_1.jpg","images/chuot-albino-thuong_2.jpg","images/chuot-albino-thuong_3.jpg","images/chuot-albino-thuong_4.jpg"]},{"slug":"chuot-albino-canh-tien","name":"Chuột Albino Cánh Tiên","price":"85k","cat":"tang-day","imgs":["images/chuot-albino-canh-tien_0.jpg","images/chuot-albino-canh-tien_1.jpg","images/chuot-albino-canh-tien_2.jpg","images/chuot-albino-canh-tien_3.jpg","images/chuot-albino-canh-tien_4.jpg"]},{"slug":"chuot-muoi-tieu-ky-cao","name":"Chuột Muối Tiêu Kỳ Cao","price":"35k","cat":"tang-day","imgs":["images/chuot-muoi-tieu-ky-cao_0.jpg","images/chuot-muoi-tieu-ky-cao_1.jpg","images/chuot-muoi-tieu-ky-cao_2.jpg","images/chuot-muoi-tieu-ky-cao_3.jpg","images/chuot-muoi-tieu-ky-cao_4.jpg"]},{"slug":"chuot-pygmy","name":"Chuột Pygmy","price":"40k","cat":"tang-day","imgs":["images/chuot-pygmy_0.jpg","images/chuot-pygmy_1.jpg","images/chuot-pygmy_2.jpg","images/chuot-pygmy_3.jpg","images/chuot-pygmy_4.jpg"]},{"slug":"chuot-hastatus","name":"Chuột Hastatus","price":"45k","cat":"tang-day","imgs":["images/chuot-hastatus_0.jpg","images/chuot-hastatus_1.jpg","images/chuot-hastatus_2.jpg","images/chuot-hastatus_3.jpg","images/chuot-hastatus_4.jpg"]},{"slug":"chuot-similis","name":"Chuột Similis","price":"90k","cat":"tang-day","imgs":["images/chuot-similis_0.jpg","images/chuot-similis_1.jpg","images/chuot-similis_2.jpg","images/chuot-similis_3.jpg","images/chuot-similis_4.jpg"]},{"slug":"chuot-adofoi","name":"Chuột Adofoi","price":"120k","cat":"tang-day","imgs":["images/chuot-adofoi_0.jpg","images/chuot-adofoi_1.jpg","images/chuot-adofoi_2.jpg","images/chuot-adofoi_3.jpg","images/chuot-adofoi_4.jpg"]},{"slug":"chuot-black-vene","name":"Chuột Black Vene","price":"90k","cat":"tang-day","imgs":["images/chuot-black-vene_0.jpg","images/chuot-black-vene_1.jpg","images/chuot-black-vene_2.jpg","images/chuot-black-vene_3.jpg","images/chuot-black-vene_4.jpg"]},{"slug":"chuot-caudi","name":"Chuột Caudi","price":"140k","cat":"tang-day","imgs":["images/chuot-caudi_0.jpg","images/chuot-caudi_1.jpg","images/chuot-caudi_2.jpg","images/chuot-caudi_3.jpg","images/chuot-caudi_4.jpg"]},{"slug":"chuot-fulleri","name":"Chuột Fulleri","price":"200k","cat":"tang-day","imgs":["images/chuot-fulleri_0.jpg","images/chuot-fulleri_1.jpg","images/chuot-fulleri_2.jpg","images/chuot-fulleri_3.jpg","images/chuot-fulleri_4.jpg"]},{"slug":"chuot-fullnli","name":"Chuột Fullnli","price":"200k","cat":"tang-day","imgs":["images/chuot-fullnli_0.jpg","images/chuot-fullnli_1.jpg","images/chuot-fullnli_2.jpg","images/chuot-fullnli_3.jpg","images/chuot-fullnli_4.jpg"]},{"slug":"chach-kuhli","name":"Chạch Kuhli","price":"25k/1con","cat":"tang-day","imgs":["images/chach-kuhli_0.jpg","images/chach-kuhli_1.jpg","images/chach-kuhli_2.jpg","images/chach-kuhli_3.jpg","images/chach-kuhli_4.jpg"]},{"slug":"bac-si-panda","name":"Bác sĩ Panda","price":"55k","cat":"tang-day","imgs":["images/bac-si-panda_0.jpg","images/bac-si-panda_1.jpg","images/bac-si-panda_2.jpg","images/bac-si-panda_3.jpg","images/bac-si-panda_4.jpg"]},{"slug":"but-chi-thai","name":"Bút Chì Thái","price":"20k","cat":"tang-day","imgs":["images/but-chi-thai_0.jpg","images/but-chi-thai_1.jpg","images/but-chi-thai_2.jpg","images/but-chi-thai_3.jpg","images/but-chi-thai_4.jpg"]},{"slug":"otto","name":"Otto","price":"65k","cat":"tang-day","imgs":["images/otto_0.jpg","images/otto_1.jpg","images/otto_2.jpg","images/otto_3.jpg","images/otto_4.jpg"]},{"slug":"ty-ba-beo-15-16cm","name":"Tỳ bà beo size 15-16cm","price":"80k","cat":"tang-day","imgs":["images/ty-ba-beo-15-16cm_0.jpg","images/ty-ba-beo-15-16cm_1.jpg","images/ty-ba-beo-15-16cm_2.jpg","images/ty-ba-beo-15-16cm_3.jpg","images/ty-ba-beo-15-16cm_4.jpg"]},{"slug":"ty-ba-beo-mini","name":"Tỳ bà beo size mini","price":"25k","cat":"tang-day","imgs":["images/ty-ba-beo-mini_0.jpg","images/ty-ba-beo-mini_1.jpg","images/ty-ba-beo-mini_2.jpg","images/ty-ba-beo-mini_3.jpg","images/ty-ba-beo-mini_4.jpg"]},{"slug":"meo-bung-bu","name":"Mèo Bụng bự","price":"70k","cat":"tang-day","imgs":["images/meo-bung-bu_0.jpg","images/meo-bung-bu_1.jpg","images/meo-bung-bu_2.jpg","images/meo-bung-bu_3.jpg","images/meo-bung-bu_4.jpg"]},{"slug":"meo-soc-dua","name":"Mèo Sọc Dưa","price":"70k","cat":"tang-day","imgs":["images/meo-soc-dua_0.jpg","images/meo-soc-dua_1.jpg","images/meo-soc-dua_2.jpg","images/meo-soc-dua_3.jpg","images/meo-soc-dua_4.jpg"]},{"slug":"meo-petricola","name":"Mèo Petricola","price":"90k","cat":"tang-day","imgs":["images/meo-petricola_0.jpg","images/meo-petricola_1.jpg","images/meo-petricola_2.jpg","images/meo-petricola_3.jpg","images/meo-petricola_4.jpg"]},{"slug":"meo-ma-thien","name":"Mèo Mã Thiên","price":"nhỏ 40k · lớn 250k","cat":"tang-day","imgs":["images/meo-ma-thien_0.jpg","images/meo-ma-thien_1.jpg","images/meo-ma-thien_2.jpg","images/meo-ma-thien_3.jpg","images/meo-ma-thien_4.jpg"]},{"slug":"meo-haplo-den","name":"Mèo Haplo Đen","price":"120k","cat":"tang-day","imgs":["images/meo-haplo-den_0.jpg","images/meo-haplo-den_1.jpg","images/meo-haplo-den_2.jpg","images/meo-haplo-den_3.jpg","images/meo-haplo-den_4.jpg"]},{"slug":"meo-haplo-albino","name":"Mèo Haplo Albino","price":"120k","cat":"tang-day","imgs":["images/meo-haplo-albino_0.jpg","images/meo-haplo-albino_1.jpg","images/meo-haplo-albino_2.jpg","images/meo-haplo-albino_3.jpg","images/meo-haplo-albino_4.jpg"]},{"slug":"pleco-l397","name":"Pleco L397","price":"180k","cat":"tang-day","imgs":["images/pleco-l397_0.jpg","images/pleco-l397_1.jpg","images/pleco-l397_2.jpg","images/pleco-l397_3.jpg","images/pleco-l397_4.jpg"]},{"slug":"pleco-l333","name":"Pleco L333","price":"150k","cat":"tang-day","imgs":["images/pleco-l333_0.jpg","images/pleco-l333_1.jpg","images/pleco-l333_2.jpg","images/pleco-l333_3.jpg","images/pleco-l333_4.jpg"]},{"slug":"pleco-l183","name":"Pleco L183","price":"120k","cat":"tang-day","imgs":["images/pleco-l183_0.jpg","images/pleco-l183_1.jpg","images/pleco-l183_2.jpg","images/pleco-l183_3.jpg","images/pleco-l183_4.jpg"]},{"slug":"pleco-l134","name":"Pleco L134","price":"300k","cat":"tang-day","imgs":["images/pleco-l134_0.jpg","images/pleco-l134_1.jpg","images/pleco-l134_2.jpg","images/pleco-l134_3.jpg","images/pleco-l134_4.jpg"]},{"slug":"pleco-l155","name":"Pleco L155","price":"500k","cat":"tang-day","imgs":["images/pleco-l155_0.jpg","images/pleco-l155_1.jpg","images/pleco-l155_2.jpg","images/pleco-l155_3.jpg","images/pleco-l155_4.jpg"]},{"slug":"tep-vang-dai","name":"Tép Vàng Đài","price":"150k/10con","cat":"tep","imgs":["images/tep-vang-dai_0.jpg","images/tep-vang-dai_1.jpg","images/tep-vang-dai_2.jpg","images/tep-vang-dai_3.jpg","images/tep-vang-dai_4.jpg"]},{"slug":"tep-vang-thai","name":"Tép Vàng Thái","price":"120k/10con","cat":"tep","imgs":["images/tep-vang-thai_0.jpg","images/tep-vang-thai_1.jpg","images/tep-vang-thai_2.jpg","images/tep-vang-thai_3.jpg","images/tep-vang-thai_4.jpg"]},{"slug":"tep-bluedream","name":"Tép BlueDream","price":"150k/10con","cat":"tep","imgs":["images/tep-bluedream_0.jpg","images/tep-bluedream_1.jpg","images/tep-bluedream_2.jpg","images/tep-bluedream_3.jpg","images/tep-bluedream_4.jpg"]},{"slug":"tep-socola","name":"Tép Socola","price":"150k/10con","cat":"tep","imgs":["images/tep-socola_0.jpg","images/tep-socola_1.jpg","images/tep-socola_2.jpg","images/tep-socola_3.jpg","images/tep-socola_4.jpg"]},{"slug":"tep-loan-mau","name":"Tép Loạn Màu","price":"170k/100con","cat":"tep","imgs":["images/tep-loan-mau_0.jpg","images/tep-loan-mau_1.jpg","images/tep-loan-mau_2.jpg","images/tep-loan-mau_3.jpg","images/tep-loan-mau_4.jpg"]},{"slug":"tep-do","name":"Tép Đỏ","price":"70k/10con · 250k/50con","cat":"tep","imgs":["images/tep-do_0.jpg","images/tep-do_1.jpg","images/tep-do_2.jpg","images/tep-do_3.jpg","images/tep-do_4.jpg"]},{"slug":"tep-rili-cam-do","name":"Tép Rili Cam/Đỏ","price":"60k/10con","cat":"tep","imgs":["images/tep-rili-cam-do_0.jpg","images/tep-rili-cam-do_1.jpg","images/tep-rili-cam-do_2.jpg","images/tep-rili-cam-do_3.jpg","images/tep-rili-cam-do_4.jpg"]},{"slug":"tep-mui-do","name":"Tép Mũi Đỏ","price":"170k/10con","cat":"tep","imgs":["images/tep-mui-do_0.jpg","images/tep-mui-do_1.jpg","images/tep-mui-do_2.jpg","images/tep-mui-do_3.jpg","images/tep-mui-do_4.jpg"]},{"slug":"tep-yamato","name":"Tép Yamato (diệt rêu tóc)","price":"35k/1con","cat":"tep","imgs":["images/tep-yamato_0.jpg","images/tep-yamato_1.jpg","images/tep-yamato_2.jpg","images/tep-yamato_3.jpg","images/tep-yamato_4.jpg"]}]